{
  "count": 228,
  "items": [
    {
      "cmtrBlncAmtChart": "3335965",
      "cntyEnglNm": "",
      "cntyCd": "",
      "cntyNm": "",
      "priodTitle": "총계",
      "expCnt": "             577,064",
      "expUsdAmt": "          47,312,704",
      "impCnt": "           1,120,738",
      "impUsdAmt": "          43,976,739",
      "cmtrBlncAmt": "           3,335,965",
      "menuId": "",
      "menuNm": "",
      "navi": "",
      "scrnId": "",
      "scrnNm": "",
      "scrnFileNm": "",
      "orderColumns": null,
      "ssSsoId": "",
      "ssOrgnCd": "",
      "ssOrgnNm": "",
      "ssCstmNm": "",
      "ssDvsnNm": "",
      "ssInotUserYn": "",
      "ssPwdInitYn": "",
      "scrType": null,
      "sord": null,
      "sidx": null,
      "page": 1,
      "rows": 10,
      "filters": null,
      "totCnt": 228,
      "ssOfpoCd": "",
      "ssOfpoNm": "",
      "grdCateJSON": null,
      "ssEmpSgn": "",
      "ssUserNm": "",
      "ssClpsNm": "",
      "ssDeptTelno": "",
      "ssUserIp": "",
      "ssAcctPuseRcd": "",
      "ssCstmSgn": "",
      "ssDvsnCd": "",
      "ssClssCd": "",
      "ssDprtCd": "",
      "ssTeamCd": "",
      "ssInfoGdCd": "",
      "frstRegstId": null,
      "lastChprId": null,
      "delYn": null,
      "ssDeptFaxNo": "",
      "firstIndex": 0,
      "lastIndex": 1,
      "recordCountPerPage": 10,
      "searchCondition": "",
      "searchKeyword": "",
      "searchUseYn": "",
      "pageIndex": 1,
      "pageUnit": 10,
      "pageSize": 10
    },
    {
      "cmtrBlncAmtChart": "4757994",
      "cntyEnglNm": "China",
      "cntyCd": "CN",
      "cntyNm": "중국",
      "priodTitle": "2013.03",
      "expCnt": "             115,433",
      "expUsdAmt": "          11,685,543",
      "impCnt": "             300,075",
      "impUsdAmt": "           6,927,548",
      "cmtrBlncAmt": "           4,757,994",
      "menuId": "",
      "menuNm": "",
      "navi": "",
      "scrnId": "",
      "scrnNm": "",
      "scrnFileNm": "",
      "orderColumns": null,
      "ssSsoId": "",
      "ssOrgnCd": "",
      "ssOrgnNm": "",
      "ssCstmNm": "",
      "ssDvsnNm": "",
      "ssInotUserYn": "",
      "ssPwdInitYn": "",
      "scrType": null,
      "sord": null,
      "sidx": null,
      "page": 1,
      "rows": 10,
      "filters": null,
      "totCnt": 228,
      "ssOfpoCd": "",
      "ssOfpoNm": "",
      "grdCateJSON": null,
      "ssEmpSgn": "",
      "ssUserNm": "",
      "ssClpsNm": "",
      "ssDeptTelno": "",
      "ssUserIp": "",
      "ssAcctPuseRcd": "",
      "ssCstmSgn": "",
      "ssDvsnCd": "",
      "ssClssCd": "",
      "ssDprtCd": "",
      "ssTeamCd": "",
      "ssInfoGdCd": "",
      "frstRegstId": null,
      "lastChprId": null,
      "delYn": null,
      "ssDeptFaxNo": "",
      "firstIndex": 0,
      "lastIndex": 1,
      "recordCountPerPage": 10,
      "searchCondition": "",
      "searchKeyword": "",
      "searchUseYn": "",
      "pageIndex": 1,
      "pageUnit": 10,
      "pageSize": 10
    },
    {
      "cmtrBlncAmtChart": "1247316",
      "cntyEnglNm": "United States",
      "cntyCd": "US",
      "cntyNm": "미국",
      "priodTitle": "2013.03",
      "expCnt": "              66,141",
      "expUsdAmt": "           4,978,892",
      "impCnt": "             444,156",
      "impUsdAmt": "           3,731,577",
      "cmtrBlncAmt": "           1,247,316",
      "menuId": "",
      "menuNm": "",
      "navi": "",
      "scrnId": "",
      "scrnNm": "",
      "scrnFileNm": "",
      "orderColumns": null,
      "ssSsoId": "",
      "ssOrgnCd": "",
      "ssOrgnNm": "",
      "ssCstmNm": "",
      "ssDvsnNm": "",
      "ssInotUserYn": "",
      "ssPwdInitYn": "",
      "scrType": null,
      "sord": null,
      "sidx": null,
      "page": 1,
      "rows": 10,
      "filters": null,
      "totCnt": 228,
      "ssOfpoCd": "",
      "ssOfpoNm": "",
      "grdCateJSON": null,
      "ssEmpSgn": "",
      "ssUserNm": "",
      "ssClpsNm": "",
      "ssDeptTelno": "",
      "ssUserIp": "",
      "ssAcctPuseRcd": "",
      "ssCstmSgn": "",
      "ssDvsnCd": "",
      "ssClssCd": "",
      "ssDprtCd": "",
      "ssTeamCd": "",
      "ssInfoGdCd": "",
      "frstRegstId": null,
      "lastChprId": null,
      "delYn": null,
      "ssDeptFaxNo": "",
      "firstIndex": 0,
      "lastIndex": 1,
      "recordCountPerPage": 10,
      "searchCondition": "",
      "searchKeyword": "",
      "searchUseYn": "",
      "pageIndex": 1,
      "pageUnit": 10,
      "pageSize": 10
    },
    {
      "cmtrBlncAmtChart": "-2631351",
      "cntyEnglNm": "Japan",
      "cntyCd": "JP",
      "cntyNm": "일본",
      "priodTitle": "2013.03",
      "expCnt": "              54,462",
      "expUsdAmt": "           2,703,277",
      "impCnt": "              80,892",
      "impUsdAmt": "           5,334,627",
      "cmtrBlncAmt": "          -2,631,351",
      "menuId": "",
      "menuNm": "",
      "navi": "",
      "scrnId": "",
      "scrnNm": "",
      "scrnFileNm": "",
      "orderColumns": null,
      "ssSsoId": "",
      "ssOrgnCd": "",
      "ssOrgnNm": "",
      "ssCstmNm": "",
      "ssDvsnNm": "",
      "ssInotUserYn": "",
      "ssPwdInitYn": "",
      "scrType": null,
      "sord": null,
      "sidx": null,
      "page": 1,
      "rows": 10,
      "filters": null,
      "totCnt": 228,
      "ssOfpoCd": "",
      "ssOfpoNm": "",
      "grdCateJSON": null,
      "ssEmpSgn": "",
      "ssUserNm": "",
      "ssClpsNm": "",
      "ssDeptTelno": "",
      "ssUserIp": "",
      "ssAcctPuseRcd": "",
      "ssCstmSgn": "",
      "ssDvsnCd": "",
      "ssClssCd": "",
      "ssDprtCd": "",
      "ssTeamCd": "",
      "ssInfoGdCd": "",
      "frstRegstId": null,
      "lastChprId": null,
      "delYn": null,
      "ssDeptFaxNo": "",
      "firstIndex": 0,
      "lastIndex": 1,
      "recordCountPerPage": 10,
      "searchCondition": "",
      "searchKeyword": "",
      "searchUseYn": "",
      "pageIndex": 1,
      "pageUnit": 10,
      "pageSize": 10
    },
    {
      "cmtrBlncAmtChart": "2412650",
      "cntyEnglNm": "Hong Kong",
      "cntyCd": "HK",
      "cntyNm": "홍콩",
      "priodTitle": "2013.03",
      "expCnt": "              32,417",
      "expUsdAmt": "           2,564,803",
      "impCnt": "              11,120",
      "impUsdAmt": "             152,153",
      "cmtrBlncAmt": "           2,412,650",
      "menuId": "",
      "menuNm": "",
      "navi": "",
      "scrnId": "",
      "scrnNm": "",
      "scrnFileNm": "",
      "orderColumns": null,
      "ssSsoId": "",
      "ssOrgnCd": "",
      "ssOrgnNm": "",
      "ssCstmNm": "",
      "ssDvsnNm": "",
      "ssInotUserYn": "",
      "ssPwdInitYn": "",
      "scrType": null,
      "sord": null,
      "sidx": null,
      "page": 1,
      "rows": 10,
      "filters": null,
      "totCnt": 228,
      "ssOfpoCd": "",
      "ssOfpoNm": "",
      "grdCateJSON": null,
      "ssEmpSgn": "",
      "ssUserNm": "",
      "ssClpsNm": "",
      "ssDeptTelno": "",
      "ssUserIp": "",
      "ssAcctPuseRcd": "",
      "ssCstmSgn": "",
      "ssDvsnCd": "",
      "ssClssCd": "",
      "ssDprtCd": "",
      "ssTeamCd": "",
      "ssInfoGdCd": "",
      "frstRegstId": null,
      "lastChprId": null,
      "delYn": null,
      "ssDeptFaxNo": "",
      "firstIndex": 0,
      "lastIndex": 1,
      "recordCountPerPage": 10,
      "searchCondition": "",
      "searchKeyword": "",
      "searchUseYn": "",
      "pageIndex": 1,
      "pageUnit": 10,
      "pageSize": 10
    },
    {
      "cmtrBlncAmtChart": "1764436",
      "cntyEnglNm": "Singapore",
      "cntyCd": "SG",
      "cntyNm": "싱가포르",
      "priodTitle": "2013.03",
      "expCnt": "              16,090",
      "expUsdAmt": "           2,564,518",
      "impCnt": "              10,040",
      "impUsdAmt": "             800,081",
      "cmtrBlncAmt": "           1,764,436",
      "menuId": "",
      "menuNm": "",
      "navi": "",
      "scrnId": "",
      "scrnNm": "",
      "scrnFileNm": "",
      "orderColumns": null,
      "ssSsoId": "",
      "ssOrgnCd": "",
      "ssOrgnNm": "",
      "ssCstmNm": "",
      "ssDvsnNm": "",
      "ssInotUserYn": "",
      "ssPwdInitYn": "",
      "scrType": null,
      "sord": null,
      "sidx": null,
      "page": 1,
      "rows": 10,
      "filters": null,
      "totCnt": 228,
      "ssOfpoCd": "",
      "ssOfpoNm": "",
      "grdCateJSON": null,
      "ssEmpSgn": "",
      "ssUserNm": "",
      "ssClpsNm": "",
      "ssDeptTelno": "",
      "ssUserIp": "",
      "ssAcctPuseRcd": "",
      "ssCstmSgn": "",
      "ssDvsnCd": "",
      "ssClssCd": "",
      "ssDprtCd": "",
      "ssTeamCd": "",
      "ssInfoGdCd": "",
      "frstRegstId": null,
      "lastChprId": null,
      "delYn": null,
      "ssDeptFaxNo": "",
      "firstIndex": 0,
      "lastIndex": 1,
      "recordCountPerPage": 10,
      "searchCondition": "",
      "searchKeyword": "",
      "searchUseYn": "",
      "pageIndex": 1,
      "pageUnit": 10,
      "pageSize": 10
    },
    {
      "cmtrBlncAmtChart": "1246913",
      "cntyEnglNm": "Viet nam",
      "cntyCd": "VN",
      "cntyNm": "베트남",
      "priodTitle": "2013.03",
      "expCnt": "              27,267",
      "expUsdAmt": "           1,827,243",
      "impCnt": "              10,208",
      "impUsdAmt": "             580,330",
      "cmtrBlncAmt": "           1,246,913",
      "menuId": "",
      "menuNm": "",
      "navi": "",
      "scrnId": "",
      "scrnNm": "",
      "scrnFileNm": "",
      "orderColumns": null,
      "ssSsoId": "",
      "ssOrgnCd": "",
      "ssOrgnNm": "",
      "ssCstmNm": "",
      "ssDvsnNm": "",
      "ssInotUserYn": "",
      "ssPwdInitYn": "",
      "scrType": null,
      "sord": null,
      "sidx": null,
      "page": 1,
      "rows": 10,
      "filters": null,
      "totCnt": 228,
      "ssOfpoCd": "",
      "ssOfpoNm": "",
      "grdCateJSON": null,
      "ssEmpSgn": "",
      "ssUserNm": "",
      "ssClpsNm": "",
      "ssDeptTelno": "",
      "ssUserIp": "",
      "ssAcctPuseRcd": "",
      "ssCstmSgn": "",
      "ssDvsnCd": "",
      "ssClssCd": "",
      "ssDprtCd": "",
      "ssTeamCd": "",
      "ssInfoGdCd": "",
      "frstRegstId": null,
      "lastChprId": null,
      "delYn": null,
      "ssDeptFaxNo": "",
      "firstIndex": 0,
      "lastIndex": 1,
      "recordCountPerPage": 10,
      "searchCondition": "",
      "searchKeyword": "",
      "searchUseYn": "",
      "pageIndex": 1,
      "pageUnit": 10,
      "pageSize": 10
    },
    {
      "cmtrBlncAmtChart": "178510",
      "cntyEnglNm": "Taiwan  Province of China",
      "cntyCd": "TW",
      "cntyNm": "대만",
      "priodTitle": "2013.03",
      "expCnt": "              17,794",
      "expUsdAmt": "           1,461,026",
      "impCnt": "              21,726",
      "impUsdAmt": "           1,282,517",
      "cmtrBlncAmt": "             178,510",
      "menuId": "",
      "menuNm": "",
      "navi": "",
      "scrnId": "",
      "scrnNm": "",
      "scrnFileNm": "",
      "orderColumns": null,
      "ssSsoId": "",
      "ssOrgnCd": "",
      "ssOrgnNm": "",
      "ssCstmNm": "",
      "ssDvsnNm": "",
      "ssInotUserYn": "",
      "ssPwdInitYn": "",
      "scrType": null,
      "sord": null,
      "sidx": null,
      "page": 1,
      "rows": 10,
      "filters": null,
      "totCnt": 228,
      "ssOfpoCd": "",
      "ssOfpoNm": "",
      "grdCateJSON": null,
      "ssEmpSgn": "",
      "ssUserNm": "",
      "ssClpsNm": "",
      "ssDeptTelno": "",
      "ssUserIp": "",
      "ssAcctPuseRcd": "",
      "ssCstmSgn": "",
      "ssDvsnCd": "",
      "ssClssCd": "",
      "ssDprtCd": "",
      "ssTeamCd": "",
      "ssInfoGdCd": "",
      "frstRegstId": null,
      "lastChprId": null,
      "delYn": null,
      "ssDeptFaxNo": "",
      "firstIndex": 0,
      "lastIndex": 1,
      "recordCountPerPage": 10,
      "searchCondition": "",
      "searchKeyword": "",
      "searchUseYn": "",
      "pageIndex": 1,
      "pageUnit": 10,
      "pageSize": 10
    },
    {
      "cmtrBlncAmtChart": "-168929",
      "cntyEnglNm": "Indonesia",
      "cntyCd": "ID",
      "cntyNm": "인도네시아",
      "priodTitle": "2013.03",
      "expCnt": "              15,323",
      "expUsdAmt": "           1,068,372",
      "impCnt": "               6,642",
      "impUsdAmt": "           1,237,301",
      "cmtrBlncAmt": "            -168,929",
      "menuId": "",
      "menuNm": "",
      "navi": "",
      "scrnId": "",
      "scrnNm": "",
      "scrnFileNm": "",
      "orderColumns": null,
      "ssSsoId": "",
      "ssOrgnCd": "",
      "ssOrgnNm": "",
      "ssCstmNm": "",
      "ssDvsnNm": "",
      "ssInotUserYn": "",
      "ssPwdInitYn": "",
      "scrType": null,
      "sord": null,
      "sidx": null,
      "page": 1,
      "rows": 10,
      "filters": null,
      "totCnt": 228,
      "ssOfpoCd": "",
      "ssOfpoNm": "",
      "grdCateJSON": null,
      "ssEmpSgn": "",
      "ssUserNm": "",
      "ssClpsNm": "",
      "ssDeptTelno": "",
      "ssUserIp": "",
      "ssAcctPuseRcd": "",
      "ssCstmSgn": "",
      "ssDvsnCd": "",
      "ssClssCd": "",
      "ssDprtCd": "",
      "ssTeamCd": "",
      "ssInfoGdCd": "",
      "frstRegstId": null,
      "lastChprId": null,
      "delYn": null,
      "ssDeptFaxNo": "",
      "firstIndex": 0,
      "lastIndex": 1,
      "recordCountPerPage": 10,
      "searchCondition": "",
      "searchKeyword": "",
      "searchUseYn": "",
      "pageIndex": 1,
      "pageUnit": 10,
      "pageSize": 10
    },
    {
      "cmtrBlncAmtChart": "585129",
      "cntyEnglNm": "India",
      "cntyCd": "IN",
      "cntyNm": "인도",
      "priodTitle": "2013.03",
      "expCnt": "              15,195",
      "expUsdAmt": "           1,017,629",
      "impCnt": "               5,715",
      "impUsdAmt": "             432,500",
      "cmtrBlncAmt": "             585,129",
      "menuId": "",
      "menuNm": "",
      "navi": "",
      "scrnId": "",
      "scrnNm": "",
      "scrnFileNm": "",
      "orderColumns": null,
      "ssSsoId": "",
      "ssOrgnCd": "",
      "ssOrgnNm": "",
      "ssCstmNm": "",
      "ssDvsnNm": "",
      "ssInotUserYn": "",
      "ssPwdInitYn": "",
      "scrType": null,
      "sord": null,
      "sidx": null,
      "page": 1,
      "rows": 10,
      "filters": null,
      "totCnt": 228,
      "ssOfpoCd": "",
      "ssOfpoNm": "",
      "grdCateJSON": null,
      "ssEmpSgn": "",
      "ssUserNm": "",
      "ssClpsNm": "",
      "ssDeptTelno": "",
      "ssUserIp": "",
      "ssAcctPuseRcd": "",
      "ssCstmSgn": "",
      "ssDvsnCd": "",
      "ssClssCd": "",
      "ssDprtCd": "",
      "ssTeamCd": "",
      "ssInfoGdCd": "",
      "frstRegstId": null,
      "lastChprId": null,
      "delYn": null,
      "ssDeptFaxNo": "",
      "firstIndex": 0,
      "lastIndex": 1,
      "recordCountPerPage": 10,
      "searchCondition": "",
      "searchKeyword": "",
      "searchUseYn": "",
      "pageIndex": 1,
      "pageUnit": 10,
      "pageSize": 10
    }
  ]
}
