{
  "count": 219,
  "items": [
    {
      "cmtrBlncAmtChart": "257733",
      "cntyEnglNm": "",
      "cntyCd": "",
      "cntyNm": "",
      "priodTitle": "총계",
      "expCnt": "             403,173",
      "expUsdAmt": "          27,287,195",
      "impCnt": "             430,998",
      "impUsdAmt": "          27,029,461",
      "cmtrBlncAmt": "             257,733",
      "menuId": "",
      "menuNm": "",
      "navi": "",
      "scrnId": "",
      "scrnNm": "",
      "scrnFileNm": "",
      "orderColumns": null,
      "ssSsoId": "",
      "ssOrgnCd": "",
      "ssOrgnNm": "",
      "ssCstmNm": "",
      "ssDvsnNm": "",
      "ssInotUserYn": "",
      "ssPwdInitYn": "",
      "scrType": null,
      "sord": null,
      "sidx": null,
      "page": 1,
      "rows": 10,
      "filters": null,
      "totCnt": 219,
      "ssOfpoCd": "",
      "ssOfpoNm": "",
      "grdCateJSON": null,
      "ssEmpSgn": "",
      "ssUserNm": "",
      "ssClpsNm": "",
      "ssDeptTelno": "",
      "ssUserIp": "",
      "ssAcctPuseRcd": "",
      "ssCstmSgn": "",
      "ssDvsnCd": "",
      "ssClssCd": "",
      "ssDprtCd": "",
      "ssTeamCd": "",
      "ssInfoGdCd": "",
      "frstRegstId": null,
      "lastChprId": null,
      "delYn": null,
      "ssDeptFaxNo": "",
      "firstIndex": 0,
      "lastIndex": 1,
      "recordCountPerPage": 10,
      "searchCondition": "",
      "searchKeyword": "",
      "searchUseYn": "",
      "pageIndex": 1,
      "pageUnit": 10,
      "pageSize": 10
    },
    {
      "cmtrBlncAmtChart": "2008802",
      "cntyEnglNm": "China",
      "cntyCd": "CN",
      "cntyNm": "중국",
      "priodTitle": "2006.08",
      "expCnt": "              83,099",
      "expUsdAmt": "           6,221,786",
      "impCnt": "             131,181",
      "impUsdAmt": "           4,212,984",
      "cmtrBlncAmt": "           2,008,802",
      "menuId": "",
      "menuNm": "",
      "navi": "",
      "scrnId": "",
      "scrnNm": "",
      "scrnFileNm": "",
      "orderColumns": null,
      "ssSsoId": "",
      "ssOrgnCd": "",
      "ssOrgnNm": "",
      "ssCstmNm": "",
      "ssDvsnNm": "",
      "ssInotUserYn": "",
      "ssPwdInitYn": "",
      "scrType": null,
      "sord": null,
      "sidx": null,
      "page": 1,
      "rows": 10,
      "filters": null,
      "totCnt": 219,
      "ssOfpoCd": "",
      "ssOfpoNm": "",
      "grdCateJSON": null,
      "ssEmpSgn": "",
      "ssUserNm": "",
      "ssClpsNm": "",
      "ssDeptTelno": "",
      "ssUserIp": "",
      "ssAcctPuseRcd": "",
      "ssCstmSgn": "",
      "ssDvsnCd": "",
      "ssClssCd": "",
      "ssDprtCd": "",
      "ssTeamCd": "",
      "ssInfoGdCd": "",
      "frstRegstId": null,
      "lastChprId": null,
      "delYn": null,
      "ssDeptFaxNo": "",
      "firstIndex": 0,
      "lastIndex": 1,
      "recordCountPerPage": 10,
      "searchCondition": "",
      "searchKeyword": "",
      "searchUseYn": "",
      "pageIndex": 1,
      "pageUnit": 10,
      "pageSize": 10
    },
    {
      "cmtrBlncAmtChart": "499041",
      "cntyEnglNm": "United States",
      "cntyCd": "US",
      "cntyNm": "미국",
      "priodTitle": "2006.08",
      "expCnt": "              52,825",
      "expUsdAmt": "           3,551,040",
      "impCnt": "              69,839",
      "impUsdAmt": "           3,051,999",
      "cmtrBlncAmt": "             499,041",
      "menuId": "",
      "menuNm": "",
      "navi": "",
      "scrnId": "",
      "scrnNm": "",
      "scrnFileNm": "",
      "orderColumns": null,
      "ssSsoId": "",
      "ssOrgnCd": "",
      "ssOrgnNm": "",
      "ssCstmNm": "",
      "ssDvsnNm": "",
      "ssInotUserYn": "",
      "ssPwdInitYn": "",
      "scrType": null,
      "sord": null,
      "sidx": null,
      "page": 1,
      "rows": 10,
      "filters": null,
      "totCnt": 219,
      "ssOfpoCd": "",
      "ssOfpoNm": "",
      "grdCateJSON": null,
      "ssEmpSgn": "",
      "ssUserNm": "",
      "ssClpsNm": "",
      "ssDeptTelno": "",
      "ssUserIp": "",
      "ssAcctPuseRcd": "",
      "ssCstmSgn": "",
      "ssDvsnCd": "",
      "ssClssCd": "",
      "ssDprtCd": "",
      "ssTeamCd": "",
      "ssInfoGdCd": "",
      "frstRegstId": null,
      "lastChprId": null,
      "delYn": null,
      "ssDeptFaxNo": "",
      "firstIndex": 0,
      "lastIndex": 1,
      "recordCountPerPage": 10,
      "searchCondition": "",
      "searchKeyword": "",
      "searchUseYn": "",
      "pageIndex": 1,
      "pageUnit": 10,
      "pageSize": 10
    },
    {
      "cmtrBlncAmtChart": "-1976739",
      "cntyEnglNm": "Japan",
      "cntyCd": "JP",
      "cntyNm": "일본",
      "priodTitle": "2006.08",
      "expCnt": "              41,445",
      "expUsdAmt": "           2,230,653",
      "impCnt": "              78,133",
      "impUsdAmt": "           4,207,391",
      "cmtrBlncAmt": "          -1,976,739",
      "menuId": "",
      "menuNm": "",
      "navi": "",
      "scrnId": "",
      "scrnNm": "",
      "scrnFileNm": "",
      "orderColumns": null,
      "ssSsoId": "",
      "ssOrgnCd": "",
      "ssOrgnNm": "",
      "ssCstmNm": "",
      "ssDvsnNm": "",
      "ssInotUserYn": "",
      "ssPwdInitYn": "",
      "scrType": null,
      "sord": null,
      "sidx": null,
      "page": 1,
      "rows": 10,
      "filters": null,
      "totCnt": 219,
      "ssOfpoCd": "",
      "ssOfpoNm": "",
      "grdCateJSON": null,
      "ssEmpSgn": "",
      "ssUserNm": "",
      "ssClpsNm": "",
      "ssDeptTelno": "",
      "ssUserIp": "",
      "ssAcctPuseRcd": "",
      "ssCstmSgn": "",
      "ssDvsnCd": "",
      "ssClssCd": "",
      "ssDprtCd": "",
      "ssTeamCd": "",
      "ssInfoGdCd": "",
      "frstRegstId": null,
      "lastChprId": null,
      "delYn": null,
      "ssDeptFaxNo": "",
      "firstIndex": 0,
      "lastIndex": 1,
      "recordCountPerPage": 10,
      "searchCondition": "",
      "searchKeyword": "",
      "searchUseYn": "",
      "pageIndex": 1,
      "pageUnit": 10,
      "pageSize": 10
    },
    {
      "cmtrBlncAmtChart": "1423119",
      "cntyEnglNm": "Hong Kong",
      "cntyCd": "HK",
      "cntyNm": "홍콩",
      "priodTitle": "2006.08",
      "expCnt": "              29,602",
      "expUsdAmt": "           1,604,949",
      "impCnt": "               8,633",
      "impUsdAmt": "             181,830",
      "cmtrBlncAmt": "           1,423,119",
      "menuId": "",
      "menuNm": "",
      "navi": "",
      "scrnId": "",
      "scrnNm": "",
      "scrnFileNm": "",
      "orderColumns": null,
      "ssSsoId": "",
      "ssOrgnCd": "",
      "ssOrgnNm": "",
      "ssCstmNm": "",
      "ssDvsnNm": "",
      "ssInotUserYn": "",
      "ssPwdInitYn": "",
      "scrType": null,
      "sord": null,
      "sidx": null,
      "page": 1,
      "rows": 10,
      "filters": null,
      "totCnt": 219,
      "ssOfpoCd": "",
      "ssOfpoNm": "",
      "grdCateJSON": null,
      "ssEmpSgn": "",
      "ssUserNm": "",
      "ssClpsNm": "",
      "ssDeptTelno": "",
      "ssUserIp": "",
      "ssAcctPuseRcd": "",
      "ssCstmSgn": "",
      "ssDvsnCd": "",
      "ssClssCd": "",
      "ssDprtCd": "",
      "ssTeamCd": "",
      "ssInfoGdCd": "",
      "frstRegstId": null,
      "lastChprId": null,
      "delYn": null,
      "ssDeptFaxNo": "",
      "firstIndex": 0,
      "lastIndex": 1,
      "recordCountPerPage": 10,
      "searchCondition": "",
      "searchKeyword": "",
      "searchUseYn": "",
      "pageIndex": 1,
      "pageUnit": 10,
      "pageSize": 10
    },
    {
      "cmtrBlncAmtChart": "262385",
      "cntyEnglNm": "Taiwan  Province of China",
      "cntyCd": "TW",
      "cntyNm": "대만",
      "priodTitle": "2006.08",
      "expCnt": "              14,031",
      "expUsdAmt": "           1,059,690",
      "impCnt": "              17,834",
      "impUsdAmt": "             797,305",
      "cmtrBlncAmt": "             262,385",
      "menuId": "",
      "menuNm": "",
      "navi": "",
      "scrnId": "",
      "scrnNm": "",
      "scrnFileNm": "",
      "orderColumns": null,
      "ssSsoId": "",
      "ssOrgnCd": "",
      "ssOrgnNm": "",
      "ssCstmNm": "",
      "ssDvsnNm": "",
      "ssInotUserYn": "",
      "ssPwdInitYn": "",
      "scrType": null,
      "sord": null,
      "sidx": null,
      "page": 1,
      "rows": 10,
      "filters": null,
      "totCnt": 219,
      "ssOfpoCd": "",
      "ssOfpoNm": "",
      "grdCateJSON": null,
      "ssEmpSgn": "",
      "ssUserNm": "",
      "ssClpsNm": "",
      "ssDeptTelno": "",
      "ssUserIp": "",
      "ssAcctPuseRcd": "",
      "ssCstmSgn": "",
      "ssDvsnCd": "",
      "ssClssCd": "",
      "ssDprtCd": "",
      "ssTeamCd": "",
      "ssInfoGdCd": "",
      "frstRegstId": null,
      "lastChprId": null,
      "delYn": null,
      "ssDeptFaxNo": "",
      "firstIndex": 0,
      "lastIndex": 1,
      "recordCountPerPage": 10,
      "searchCondition": "",
      "searchKeyword": "",
      "searchUseYn": "",
      "pageIndex": 1,
      "pageUnit": 10,
      "pageSize": 10
    },
    {
      "cmtrBlncAmtChart": "309620",
      "cntyEnglNm": "Singapore",
      "cntyCd": "SG",
      "cntyNm": "싱가포르",
      "priodTitle": "2006.08",
      "expCnt": "              13,114",
      "expUsdAmt": "             780,835",
      "impCnt": "               9,708",
      "impUsdAmt": "             471,215",
      "cmtrBlncAmt": "             309,620",
      "menuId": "",
      "menuNm": "",
      "navi": "",
      "scrnId": "",
      "scrnNm": "",
      "scrnFileNm": "",
      "orderColumns": null,
      "ssSsoId": "",
      "ssOrgnCd": "",
      "ssOrgnNm": "",
      "ssCstmNm": "",
      "ssDvsnNm": "",
      "ssInotUserYn": "",
      "ssPwdInitYn": "",
      "scrType": null,
      "sord": null,
      "sidx": null,
      "page": 1,
      "rows": 10,
      "filters": null,
      "totCnt": 219,
      "ssOfpoCd": "",
      "ssOfpoNm": "",
      "grdCateJSON": null,
      "ssEmpSgn": "",
      "ssUserNm": "",
      "ssClpsNm": "",
      "ssDeptTelno": "",
      "ssUserIp": "",
      "ssAcctPuseRcd": "",
      "ssCstmSgn": "",
      "ssDvsnCd": "",
      "ssClssCd": "",
      "ssDprtCd": "",
      "ssTeamCd": "",
      "ssInfoGdCd": "",
      "frstRegstId": null,
      "lastChprId": null,
      "delYn": null,
      "ssDeptFaxNo": "",
      "firstIndex": 0,
      "lastIndex": 1,
      "recordCountPerPage": 10,
      "searchCondition": "",
      "searchKeyword": "",
      "searchUseYn": "",
      "pageIndex": 1,
      "pageUnit": 10,
      "pageSize": 10
    },
    {
      "cmtrBlncAmtChart": "-247669",
      "cntyEnglNm": "Germany",
      "cntyCd": "DE",
      "cntyNm": "독일",
      "priodTitle": "2006.08",
      "expCnt": "               9,610",
      "expUsdAmt": "             717,683",
      "impCnt": "              23,425",
      "impUsdAmt": "             965,353",
      "cmtrBlncAmt": "            -247,669",
      "menuId": "",
      "menuNm": "",
      "navi": "",
      "scrnId": "",
      "scrnNm": "",
      "scrnFileNm": "",
      "orderColumns": null,
      "ssSsoId": "",
      "ssOrgnCd": "",
      "ssOrgnNm": "",
      "ssCstmNm": "",
      "ssDvsnNm": "",
      "ssInotUserYn": "",
      "ssPwdInitYn": "",
      "scrType": null,
      "sord": null,
      "sidx": null,
      "page": 1,
      "rows": 10,
      "filters": null,
      "totCnt": 219,
      "ssOfpoCd": "",
      "ssOfpoNm": "",
      "grdCateJSON": null,
      "ssEmpSgn": "",
      "ssUserNm": "",
      "ssClpsNm": "",
      "ssDeptTelno": "",
      "ssUserIp": "",
      "ssAcctPuseRcd": "",
      "ssCstmSgn": "",
      "ssDvsnCd": "",
      "ssClssCd": "",
      "ssDprtCd": "",
      "ssTeamCd": "",
      "ssInfoGdCd": "",
      "frstRegstId": null,
      "lastChprId": null,
      "delYn": null,
      "ssDeptFaxNo": "",
      "firstIndex": 0,
      "lastIndex": 1,
      "recordCountPerPage": 10,
      "searchCondition": "",
      "searchKeyword": "",
      "searchUseYn": "",
      "pageIndex": 1,
      "pageUnit": 10,
      "pageSize": 10
    },
    {
      "cmtrBlncAmtChart": "586441",
      "cntyEnglNm": "Mexico",
      "cntyCd": "MX",
      "cntyNm": "멕시코",
      "priodTitle": "2006.08",
      "expCnt": "               6,229",
      "expUsdAmt": "             645,256",
      "impCnt": "               1,498",
      "impUsdAmt": "              58,815",
      "cmtrBlncAmt": "             586,441",
      "menuId": "",
      "menuNm": "",
      "navi": "",
      "scrnId": "",
      "scrnNm": "",
      "scrnFileNm": "",
      "orderColumns": null,
      "ssSsoId": "",
      "ssOrgnCd": "",
      "ssOrgnNm": "",
      "ssCstmNm": "",
      "ssDvsnNm": "",
      "ssInotUserYn": "",
      "ssPwdInitYn": "",
      "scrType": null,
      "sord": null,
      "sidx": null,
      "page": 1,
      "rows": 10,
      "filters": null,
      "totCnt": 219,
      "ssOfpoCd": "",
      "ssOfpoNm": "",
      "grdCateJSON": null,
      "ssEmpSgn": "",
      "ssUserNm": "",
      "ssClpsNm": "",
      "ssDeptTelno": "",
      "ssUserIp": "",
      "ssAcctPuseRcd": "",
      "ssCstmSgn": "",
      "ssDvsnCd": "",
      "ssClssCd": "",
      "ssDprtCd": "",
      "ssTeamCd": "",
      "ssInfoGdCd": "",
      "frstRegstId": null,
      "lastChprId": null,
      "delYn": null,
      "ssDeptFaxNo": "",
      "firstIndex": 0,
      "lastIndex": 1,
      "recordCountPerPage": 10,
      "searchCondition": "",
      "searchKeyword": "",
      "searchUseYn": "",
      "pageIndex": 1,
      "pageUnit": 10,
      "pageSize": 10
    },
    {
      "cmtrBlncAmtChart": "135535",
      "cntyEnglNm": "India",
      "cntyCd": "IN",
      "cntyNm": "인도",
      "priodTitle": "2006.08",
      "expCnt": "               7,033",
      "expUsdAmt": "             510,716",
      "impCnt": "               2,994",
      "impUsdAmt": "             375,180",
      "cmtrBlncAmt": "             135,535",
      "menuId": "",
      "menuNm": "",
      "navi": "",
      "scrnId": "",
      "scrnNm": "",
      "scrnFileNm": "",
      "orderColumns": null,
      "ssSsoId": "",
      "ssOrgnCd": "",
      "ssOrgnNm": "",
      "ssCstmNm": "",
      "ssDvsnNm": "",
      "ssInotUserYn": "",
      "ssPwdInitYn": "",
      "scrType": null,
      "sord": null,
      "sidx": null,
      "page": 1,
      "rows": 10,
      "filters": null,
      "totCnt": 219,
      "ssOfpoCd": "",
      "ssOfpoNm": "",
      "grdCateJSON": null,
      "ssEmpSgn": "",
      "ssUserNm": "",
      "ssClpsNm": "",
      "ssDeptTelno": "",
      "ssUserIp": "",
      "ssAcctPuseRcd": "",
      "ssCstmSgn": "",
      "ssDvsnCd": "",
      "ssClssCd": "",
      "ssDprtCd": "",
      "ssTeamCd": "",
      "ssInfoGdCd": "",
      "frstRegstId": null,
      "lastChprId": null,
      "delYn": null,
      "ssDeptFaxNo": "",
      "firstIndex": 0,
      "lastIndex": 1,
      "recordCountPerPage": 10,
      "searchCondition": "",
      "searchKeyword": "",
      "searchUseYn": "",
      "pageIndex": 1,
      "pageUnit": 10,
      "pageSize": 10
    }
  ]
}
